programmingquotes/__init__.py
programmingquotes/cli.py
programmingquotes/pq.py
programmingquotes/quotes.json
programmingquotes-2.0.0.dist-info/DESCRIPTION.rst
programmingquotes-2.0.0.dist-info/METADATA
programmingquotes-2.0.0.dist-info/RECORD
programmingquotes-2.0.0.dist-info/WHEEL
programmingquotes-2.0.0.dist-info/entry_points.txt
programmingquotes-2.0.0.dist-info/metadata.json
programmingquotes-2.0.0.dist-info/top_level.txt
