Metadata-Version: 2.0
Name: programmingquotes
Version: 2.0.0
Summary: Output great/funny programming quotes. Best to use with something like fish_greeting
Home-page: https://github.com/FancyChaos/programmingquotes
Author: Felix Scheja
Author-email: Felix.Scheja@outlook.de
License: MIT license
Keywords: programmingquotes
Platform: UNKNOWN
Requires-Dist: Click (>=6.0)
